sparkplug_notifications/__init__.py
sparkplug_notifications/apps.py
sparkplug_notifications/enums/__init__.py
sparkplug_notifications/enums/client.py
sparkplug_notifications/factories.py
sparkplug_notifications/migrations/0001_initial.py
sparkplug_notifications/migrations/0002_alter_notification_options.py
sparkplug_notifications/migrations/0003_alter_notification_managers.py
sparkplug_notifications/migrations/0004_rename_read_notification_has_read_and_more.py
sparkplug_notifications/migrations/0005_alter_notification_created_and_more.py
sparkplug_notifications/migrations/__init__.py
sparkplug_notifications/models/__init__.py
sparkplug_notifications/models/notification.py
sparkplug_notifications/queries/__init__.py
sparkplug_notifications/queries/notifications_list.py
sparkplug_notifications/queries/unread_count.py
sparkplug_notifications/rules/__init__.py
sparkplug_notifications/rules/is_recipient.py
sparkplug_notifications/serializers/__init__.py
sparkplug_notifications/serializers/detail.py
sparkplug_notifications/serializers/list_filter.py
sparkplug_notifications/services/__init__.py
sparkplug_notifications/services/mark_read.py
sparkplug_notifications/services/send_notification.py
sparkplug_notifications/tasks.py
sparkplug_notifications/tests/__init__.py
sparkplug_notifications/tests/queries/__init__.py
sparkplug_notifications/tests/queries/test_notifications_list.py
sparkplug_notifications/tests/queries/test_unread_count.py
sparkplug_notifications/tests/serializers/__init__.py
sparkplug_notifications/tests/serializers/test_detail.py
sparkplug_notifications/tests/serializers/test_list_filter.py
sparkplug_notifications/tests/services/__init__.py
sparkplug_notifications/tests/services/test_mark_read.py
sparkplug_notifications/tests/services/test_send_notification.py
sparkplug_notifications/tests/test_rules.py
sparkplug_notifications/tests/utils.py
sparkplug_notifications/tests/views/__init__.py
sparkplug_notifications/tests/views/test_list.py
sparkplug_api_notifications-1.1.5.dist-info/METADATA
sparkplug_api_notifications-1.1.5.dist-info/WHEEL
sparkplug_api_notifications-1.1.5.dist-info/RECORD
