Metadata-Version: 2.3
Name: sparkplug-api-notifications
Version: 1.1.5
Summary: Notifications package for Sparkplug apps
License: MIT
Author: Sparkplug Marcus
Author-email: sparkplugmarcus@gmail.com
Requires-Python: >=3.11,<4.0
Classifier: License :: OSI Approved :: MIT License
Classifier: Programming Language :: Python :: 3
Classifier: Programming Language :: Python :: 3.11
Classifier: Programming Language :: Python :: 3.12
Classifier: Programming Language :: Python :: 3.13
Requires-Dist: django-postgres-extra (>=2.0.9,<2.1.0)
Requires-Dist: sparkplug-api-core (>=1.1.5,<1.2.0)
